CZDS_utils/__init__.py
CZDS_utils/czds_json_utils.py
CZDS_utils/czds_utils.py
czds_utils-1.9.1.dist-info/licenses/LICENSE
czds_utils-1.9.1.dist-info/METADATA
czds_utils-1.9.1.dist-info/WHEEL
czds_utils-1.9.1.dist-info/top_level.txt
czds_utils-1.9.1.dist-info/RECORD
