Metadata-Version: 2.4
Name: CZDS-utils
Version: 1.9.1
Summary: Tools for processing XAS spectra.
Author-email: James Moraes de Almeida <james@almeida.page>
Classifier: Programming Language :: Python :: 3
Classifier: License :: OSI Approved :: MIT License
Classifier: Operating System :: OS Independent
Requires-Python: >=3.8
License-File: LICENSE
Requires-Dist: numpy
Requires-Dist: pandas
Requires-Dist: scikit-learn
Requires-Dist: regex
Requires-Dist: scipy
Requires-Dist: lmfit
Requires-Dist: matplotlib
Dynamic: license-file
